{"files":[{"name":"Business English Technology Vocabulary for IT - Web 2.0","size":"9.39MB","length":9851347,"children":null,"url":"https://laof.github.io/em/src/assets/mp3/Business English Technology Vocabulary for IT - Web 2.0.MP3","time":615.7060993602945,"lrc":"https://laof.github.io/em/src/assets/mp3/Business English Technology Vocabulary for IT - Web 2.0.lrc"},{"name":"Dialogues at Work1-7","size":"10.65MB","length":11171263,"children":null,"url":"https://laof.github.io/em/src/assets/mp3/Dialogues at Work1-7.MP3","time":698.2007901443694,"lrc":"https://laof.github.io/em/src/assets/mp3/Dialogues at Work1-7.lrc"},{"name":"Dialogues at Work13-end","size":"35.08MB","length":36784637,"children":null,"url":"https://laof.github.io/em/src/assets/mp3/Dialogues at Work13-end.MP3","time":2299.0366484818232,"lrc":"https://laof.github.io/em/src/assets/mp3/Dialogues at Work13-end.lrc"},{"name":"Dialogues at Work8-13","size":"34.59MB","length":36269294,"children":null,"url":"https://laof.github.io/em/src/assets/mp3/Dialogues at Work8-13.MP3","time":2266.827670097794,"lrc":"https://laof.github.io/em/src/assets/mp3/Dialogues at Work8-13.lrc"},{"name":"English Vocabulary for IT VV 25 - Internet Technol","size":"9.38MB","length":9840481,"children":null,"url":"https://laof.github.io/em/src/assets/mp3/English Vocabulary for IT VV 25 - Internet Technol.MP3","time":615.0269157122939,"lrc":"https://laof.github.io/em/src/assets/mp3/English Vocabulary for IT VV 25 - Internet Technol.lrc"},{"name":"Technical English VV 24 - Internet Technology","size":"10.32MB","length":10816833,"children":null,"url":"https://laof.github.io/em/src/assets/mp3/Technical English VV 24 - Internet Technology.MP3","time":676.0489542403493,"lrc":"https://laof.github.io/em/src/assets/mp3/Technical English VV 24 - Internet Technology.lrc"},{"name":"loulan","size":"5.03MB","length":5274423,"children":null,"url":"https://laof.github.io/em/src/assets/mp3/loulan.mp3","time":329.62504886403474,"lrc":"https://laof.github.io/em/src/assets/mp3/loulan.lrc"}],"time":"2023-06-11 16:33:39"}